deep_chess_playground/__init__.py
deep_chess_playground/data_encoders/__init__.py
deep_chess_playground/data_encoders/input_encoders/__init__.py
deep_chess_playground/data_encoders/input_encoders/grid_encoding.py
deep_chess_playground/data_encoders/output_encoders/__init__.py
deep_chess_playground/data_encoders/output_encoders/move_encoding_8_8_73.py
deep_chess_playground/lightning_modules/__init__.py
deep_chess_playground/lightning_modules/basic_module.py
deep_chess_playground/lightning_modules/binary_classifier.py
deep_chess_playground/lightning_modules/lightning_module_factory.py
deep_chess_playground/lightning_modules/multiclass_classifier.py
deep_chess_playground/lightning_modules/regressor.py
deep_chess_playground/pytorch_modules/__init__.py
deep_chess_playground/pytorch_modules/cnn/__init__.py
deep_chess_playground/pytorch_modules/cnn/one_d_cnn/__init__.py
deep_chess_playground/pytorch_modules/cnn/three_d_cnn/__init__.py
deep_chess_playground/pytorch_modules/cnn/two_d_cnn/__init__.py
deep_chess_playground/pytorch_modules/cnn/two_d_cnn/backbones.py
deep_chess_playground/pytorch_modules/cnn/two_d_cnn/heads.py
deep_chess_playground/pytorch_modules/cnn/two_d_cnn/simple_modules.py
deep_chess_playground/pytorch_modules/fcn/__init__.py
deep_chess_playground/pytorch_modules/fcn/nnue/__init__.py
deep_chess_playground/pytorch_modules/fcn/piece_centric/__init__.py
deep_chess_playground/pytorch_modules/transformer/__init__.py
deep_chess_playground/utils/__init__.py
deep_chess_playground/utils/headers.py
deep_chess_playground/utils/move_utilities.py
deep_chess_playground/utils/pgn_zst_to_csv_gz_converter.py
deep_chess_playground/utils/square_utilities.py
deep_chess_playground-0.0.4.dist-info/LICENSE
deep_chess_playground-0.0.4.dist-info/METADATA
deep_chess_playground-0.0.4.dist-info/WHEEL
deep_chess_playground-0.0.4.dist-info/RECORD
