Metadata-Version: 2.1
Name: deep-chess-playground
Version: 0.0.4
Summary: Where deep learning meets chess
Home-page: https://github.com/PypayaTech/deep-chess-playground
License: MIT
Keywords: chess,deep learning,neural networks
Author: PypayaTech
Requires-Python: >=3.10,<4.0
Classifier: Intended Audience :: Developers
Classifier: License :: OSI Approved :: MIT License
Classifier: Operating System :: OS Independent
Classifier: Programming Language :: Python :: 3
Classifier: Programming Language :: Python :: 3.10
Classifier: Programming Language :: Python :: 3.11
Classifier: Programming Language :: Python :: 3.12
Requires-Dist: chess (>=1.10.0,<2.0.0)
Requires-Dist: numpy (>=1.10.0,<2.0.0)
Requires-Dist: pandas (>=2.0.0,<3.0.0)
Requires-Dist: pypaya-pgn-parser (>=0.1.0,<0.2.0)
Requires-Dist: pypaya-python-tools (>=1.1.0,<2.0.0)
Requires-Dist: zstandard (>=0.23.0,<0.24.0)
Project-URL: Repository, https://github.com/PypayaTech/deep-chess-playground
